grnviz/__init__.py
grnviz-0.1.1.dist-info/METADATA
grnviz-0.1.1.dist-info/WHEEL
grnviz-0.1.1.dist-info/licenses/LICENSE.txt
grnviz-0.1.1.dist-info/RECORD
